xpath_utils/__init__.py
xpath_utils/xpath_utils.py
xpath_utils/models/__init__.py
xpath_utils/models/xpath_attribute_value.py
xpath_utils/models/xpath_attribute_value_contains.py
xpath_utils/models/xpath_attribute_value_equals.py
xpath_utils/models/xpath_attribute_value_starts_with.py
xpath_utils/models/xpath_condition.py
xpath_utils/models/xpath_condition_contains.py
xpath_utils/models/xpath_condition_equals.py
xpath_utils/models/xpath_condition_starts_with.py
xpath_utils/models/enums/__init__.py
xpath_utils/models/enums/xpath_condition_relation.py
xpath_utils/models/enums/xpath_condition_type.py
xpath_utils-0.0.3.dist-info/LICENSE
xpath_utils-0.0.3.dist-info/METADATA
xpath_utils-0.0.3.dist-info/WHEEL
xpath_utils-0.0.3.dist-info/top_level.txt
xpath_utils-0.0.3.dist-info/RECORD
